{"fileName": "vc_25_150_02.txt", "graph": {"n": 25, "m": 150, "d": 0.5}, "problemClass": "SPI", "testInstanceName": "150", "testInstanceVersion": "02.txt", "performanceMetrics": {"generations": [{"best": 1156.0, "objective": 1156, "avg": 2919.8975, "evals": 635}, {"best": 1132.0, "objective": 1132, "avg": 2839.1725, "evals": 867}, {"best": 1132.0, "objective": 1132, "avg": 2501.855, "evals": 1080}, {"best": 1132.0, "objective": 1132, "avg": 2535.2125, "evals": 1320}, {"best": 1132.0, "objective": 1132, "avg": 2429.0525, "evals": 1540}, {"best": 1132.0, "objective": 1132, "avg": 3178.8275, "evals": 1791}, {"best": 1132.0, "objective": 1132, "avg": 2827.1875, "evals": 2020}, {"best": 1132.0, "objective": 1132, "avg": 3142.655, "evals": 2254}, {"best": 1132.0, "objective": 1132, "avg": 2928.5125, "evals": 2500}, {"best": 1132.0, "objective": 1132, "avg": 3036.2175, "evals": 2745}, {"best": 1132.0, "objective": 1132, "avg": 3493.635, "evals": 2987}, {"best": 1132.0, "objective": 1132, "avg": 3099.4025, "evals": 3232}, {"best": 1132.0, "objective": 1132, "avg": 2800.015, "evals": 3469}, {"best": 1132.0, "objective": 1132, "avg": 2757.1275, "evals": 3725}, {"best": 1132.0, "objective": 1132, "avg": 2813.915, "evals": 3978}, {"best": 1132.0, "objective": 1132, "avg": 2500.03, "evals": 4203}, {"best": 1132.0, "objective": 1132, "avg": 2522.2725, "evals": 4454}, {"best": 1132.0, "objective": 1132, "avg": 2872.6375, "evals": 4688}, {"best": 1132.0, "objective": 1132, "avg": 3000.175, "evals": 4947}, {"best": 1132.0, "objective": 1132, "avg": 3036.515, "evals": 5195}, {"best": 1132.0, "objective": 1132, "avg": 2986.6325, "evals": 5453}, {"best": 1132.0, "objective": 1132, "avg": 3001.4775, "evals": 5702}, {"best": 1132.0, "objective": 1132, "avg": 2825.2325, "evals": 5940}, {"best": 1132.0, "objective": 1132, "avg": 2681.5975, "evals": 6170}, {"best": 1132.0, "objective": 1132, "avg": 2693.9075, "evals": 6423}, {"best": 1132.0, "objective": 1132, "avg": 2721.4825, "evals": 6665}, {"best": 1132.0, "objective": 1132, "avg": 3180.7425, "evals": 6923}, {"best": 1132.0, "objective": 1132, "avg": 2842.29, "evals": 7177}, {"best": 1132.0, "objective": 1132, "avg": 2901.78, "evals": 7426}, {"best": 1132.0, "objective": 1132, "avg": 3181.195, "evals": 7691}, {"best": 1132.0, "objective": 1132, "avg": 3101.5575, "evals": 7954}, {"best": 1132.0, "objective": 1132, "avg": 2843.44, "evals": 8202}, {"best": 1132.0, "objective": 1132, "avg": 3099.1, "evals": 8451}, {"best": 1132.0, "objective": 1132, "avg": 2451.85, "evals": 8691}, {"best": 1132.0, "objective": 1132, "avg": 3107.725, "evals": 8933}, {"best": 1132.0, "objective": 1132, "avg": 2370.2225, "evals": 9143}, {"best": 1132.0, "objective": 1132, "avg": 2699.8, "evals": 9384}, {"best": 1132.0, "objective": 1132, "avg": 3136.5875, "evals": 9637}, {"best": 1132.0, "objective": 1132, "avg": 2729.445, "evals": 9872}, {"best": 1132.0, "objective": 1132, "avg": 3408.6975, "evals": 10132}, {"best": 1132.0, "objective": 1132, "avg": 3069.6675, "evals": 10377}, {"best": 1132.0, "objective": 1132, "avg": 2956.7175, "evals": 10617}], "best_objective": 1132}}