{"fileName": "vc_20_120_03.txt", "graph": {"n": 20, "m": 120, "d": 0.631578947368421}, "problemClass": "SPI", "testInstanceName": "120", "testInstanceVersion": "03.txt", "performanceMetrics": {"generations": [{"best": 994.0, "objective": 994, "avg": 2027.28, "evals": 219}, {"best": 994.0, "objective": 994, "avg": 2263.5466666666666, "evals": 289}, {"best": 994.0, "objective": 994, "avg": 2133.6133333333332, "evals": 391}, {"best": 994.0, "objective": 994, "avg": 2342.04, "evals": 487}, {"best": 994.0, "objective": 994, "avg": 1682.82, "evals": 575}, {"best": 994.0, "objective": 994, "avg": 1751.5, "evals": 654}, {"best": 994.0, "objective": 994, "avg": 2109.38, "evals": 738}, {"best": 994.0, "objective": 994, "avg": 2209.96, "evals": 837}, {"best": 994.0, "objective": 994, "avg": 1879.8133333333333, "evals": 929}, {"best": 994.0, "objective": 994, "avg": 2064.8733333333334, "evals": 1016}, {"best": 994.0, "objective": 994, "avg": 2067.54, "evals": 1107}, {"best": 994.0, "objective": 994, "avg": 1708.7, "evals": 1193}, {"best": 994.0, "objective": 994, "avg": 1952.1666666666667, "evals": 1287}, {"best": 994.0, "objective": 994, "avg": 1481.4933333333333, "evals": 1367}, {"best": 994.0, "objective": 994, "avg": 1867.3466666666666, "evals": 1463}, {"best": 994.0, "objective": 994, "avg": 1780.04, "evals": 1546}, {"best": 994.0, "objective": 994, "avg": 1837.8733333333332, "evals": 1632}, {"best": 994.0, "objective": 994, "avg": 2851.366666666667, "evals": 1728}, {"best": 994.0, "objective": 994, "avg": 1838.4866666666667, "evals": 1810}, {"best": 994.0, "objective": 994, "avg": 1622.4866666666667, "evals": 1897}, {"best": 994.0, "objective": 994, "avg": 2053.92, "evals": 1977}, {"best": 994.0, "objective": 994, "avg": 2152.8733333333334, "evals": 2070}, {"best": 994.0, "objective": 994, "avg": 2367.326666666667, "evals": 2168}, {"best": 994.0, "objective": 994, "avg": 2420.653333333333, "evals": 2255}, {"best": 994.0, "objective": 994, "avg": 2193.5133333333333, "evals": 2348}, {"best": 994.0, "objective": 994, "avg": 1899.18, "evals": 2441}, {"best": 994.0, "objective": 994, "avg": 1922.6933333333334, "evals": 2532}, {"best": 994.0, "objective": 994, "avg": 1877.9933333333333, "evals": 2627}, {"best": 994.0, "objective": 994, "avg": 1970.0733333333333, "evals": 2727}, {"best": 994.0, "objective": 994, "avg": 2241.693333333333, "evals": 2820}, {"best": 994.0, "objective": 994, "avg": 1985.06, "evals": 2920}, {"best": 994.0, "objective": 994, "avg": 1977.9933333333333, "evals": 3018}, {"best": 994.0, "objective": 994, "avg": 2324.5933333333332, "evals": 3102}, {"best": 994.0, "objective": 994, "avg": 2024.4466666666667, "evals": 3188}, {"best": 994.0, "objective": 994, "avg": 1837.2333333333333, "evals": 3283}, {"best": 994.0, "objective": 994, "avg": 1682.14, "evals": 3374}, {"best": 994.0, "objective": 994, "avg": 1867.52, "evals": 3463}, {"best": 994.0, "objective": 994, "avg": 2350.38, "evals": 3558}, {"best": 994.0, "objective": 994, "avg": 1853.2133333333334, "evals": 3645}, {"best": 994.0, "objective": 994, "avg": 1692.84, "evals": 3748}, {"best": 994.0, "objective": 994, "avg": 1795.2666666666667, "evals": 3830}, {"best": 994.0, "objective": 994, "avg": 1795.3333333333333, "evals": 3910}, {"best": 994.0, "objective": 994, "avg": 2054.366666666667, "evals": 4002}, {"best": 994.0, "objective": 994, "avg": 1736.24, "evals": 4089}, {"best": 994.0, "objective": 994, "avg": 1681.7133333333334, "evals": 4186}, {"best": 994.0, "objective": 994, "avg": 1797.32, "evals": 4271}, {"best": 994.0, "objective": 994, "avg": 1878.9066666666668, "evals": 4361}, {"best": 994.0, "objective": 994, "avg": 1366.46, "evals": 4449}, {"best": 994.0, "objective": 994, "avg": 2041.9533333333334, "evals": 4542}, {"best": 994.0, "objective": 994, "avg": 1850.5933333333332, "evals": 4637}, {"best": 994.0, "objective": 994, "avg": 1885.0066666666667, "evals": 4728}, {"best": 994.0, "objective": 994, "avg": 2153.133333333333, "evals": 4817}, {"best": 994.0, "objective": 994, "avg": 1878.76, "evals": 4919}, {"best": 994.0, "objective": 994, "avg": 2951.0533333333333, "evals": 5007}, {"best": 994.0, "objective": 994, "avg": 1954.0, "evals": 5100}, {"best": 994.0, "objective": 994, "avg": 1809.5866666666666, "evals": 5199}, {"best": 994.0, "objective": 994, "avg": 1936.8933333333334, "evals": 5293}, {"best": 994.0, "objective": 994, "avg": 1781.3066666666666, "evals": 5398}, {"best": 994.0, "objective": 994, "avg": 2238.36, "evals": 5487}, {"best": 994.0, "objective": 994, "avg": 1837.4466666666667, "evals": 5582}, {"best": 994.0, "objective": 994, "avg": 1923.02, "evals": 5665}, {"best": 994.0, "objective": 994, "avg": 1825.4133333333334, "evals": 5765}, {"best": 994.0, "objective": 994, "avg": 1907.5, "evals": 5857}, {"best": 994.0, "objective": 994, "avg": 1837.4333333333334, "evals": 5942}, {"best": 994.0, "objective": 994, "avg": 1694.2533333333333, "evals": 6040}, {"best": 994.0, "objective": 994, "avg": 1566.3733333333332, "evals": 6132}, {"best": 994.0, "objective": 994, "avg": 2307.6066666666666, "evals": 6222}, {"best": 994.0, "objective": 994, "avg": 1907.9333333333334, "evals": 6314}, {"best": 994.0, "objective": 994, "avg": 1984.2066666666667, "evals": 6407}, {"best": 994.0, "objective": 994, "avg": 1938.68, "evals": 6490}, {"best": 994.0, "objective": 994, "avg": 1895.18, "evals": 6582}, {"best": 994.0, "objective": 994, "avg": 1951.18, "evals": 6659}, {"best": 994.0, "objective": 994, "avg": 1993.38, "evals": 6744}, {"best": 994.0, "objective": 994, "avg": 1823.56, "evals": 6826}, {"best": 994.0, "objective": 994, "avg": 2066.5, "evals": 6915}, {"best": 994.0, "objective": 994, "avg": 1766.3066666666666, "evals": 7009}, {"best": 994.0, "objective": 994, "avg": 2036.58, "evals": 7104}, {"best": 994.0, "objective": 994, "avg": 2123.0866666666666, "evals": 7201}, {"best": 994.0, "objective": 994, "avg": 2322.76, "evals": 7284}, {"best": 994.0, "objective": 994, "avg": 2452.9733333333334, "evals": 7383}, {"best": 994.0, "objective": 994, "avg": 1966.4666666666667, "evals": 7474}, {"best": 994.0, "objective": 994, "avg": 1740.8, "evals": 7570}, {"best": 994.0, "objective": 994, "avg": 1750.4466666666667, "evals": 7654}, {"best": 994.0, "objective": 994, "avg": 1923.1666666666667, "evals": 7753}, {"best": 994.0, "objective": 994, "avg": 1897.4266666666667, "evals": 7852}, {"best": 994.0, "objective": 994, "avg": 2040.2, "evals": 7951}, {"best": 994.0, "objective": 994, "avg": 2636.786666666667, "evals": 8040}, {"best": 994.0, "objective": 994, "avg": 2209.0266666666666, "evals": 8134}, {"best": 994.0, "objective": 994, "avg": 2269.0733333333333, "evals": 8240}, {"best": 994.0, "objective": 994, "avg": 1766.0066666666667, "evals": 8320}, {"best": 994.0, "objective": 994, "avg": 1852.2466666666667, "evals": 8413}, {"best": 994.0, "objective": 994, "avg": 1653.0333333333333, "evals": 8513}, {"best": 994.0, "objective": 994, "avg": 2627.0533333333333, "evals": 8604}, {"best": 994.0, "objective": 994, "avg": 2321.3333333333335, "evals": 8693}, {"best": 994.0, "objective": 994, "avg": 2166.2266666666665, "evals": 8786}, {"best": 994.0, "objective": 994, "avg": 2066.5866666666666, "evals": 8867}, {"best": 994.0, "objective": 994, "avg": 1552.1733333333334, "evals": 8957}, {"best": 994.0, "objective": 994, "avg": 1908.8333333333333, "evals": 9048}, {"best": 994.0, "objective": 994, "avg": 1794.18, "evals": 9141}, {"best": 994.0, "objective": 994, "avg": 2004.94, "evals": 9231}, {"best": 994.0, "objective": 994, "avg": 1997.0666666666666, "evals": 9317}, {"best": 994.0, "objective": 994, "avg": 1979.3666666666666, "evals": 9410}, {"best": 994.0, "objective": 994, "avg": 1879.9466666666667, "evals": 9503}, {"best": 994.0, "objective": 994, "avg": 1811.0266666666666, "evals": 9603}, {"best": 994.0, "objective": 994, "avg": 1638.4333333333334, "evals": 9677}, {"best": 994.0, "objective": 994, "avg": 2137.84, "evals": 9773}, {"best": 994.0, "objective": 994, "avg": 1883.3333333333333, "evals": 9854}, {"best": 994.0, "objective": 994, "avg": 1968.9733333333334, "evals": 9940}, {"best": 994.0, "objective": 994, "avg": 1981.5533333333333, "evals": 10045}, {"best": 994.0, "objective": 994, "avg": 1495.8666666666666, "evals": 10126}, {"best": 994.0, "objective": 994, "avg": 1853.6, "evals": 10207}, {"best": 994.0, "objective": 994, "avg": 2150.786666666667, "evals": 10287}, {"best": 994.0, "objective": 994, "avg": 2238.74, "evals": 10374}, {"best": 994.0, "objective": 994, "avg": 1724.7, "evals": 10477}, {"best": 994.0, "objective": 994, "avg": 1780.7666666666667, "evals": 10562}, {"best": 994.0, "objective": 994, "avg": 1638.66, "evals": 10654}, {"best": 994.0, "objective": 994, "avg": 1806.9133333333334, "evals": 10745}, {"best": 994.0, "objective": 994, "avg": 1981.3666666666666, "evals": 10851}, {"best": 994.0, "objective": 994, "avg": 1509.5933333333332, "evals": 10939}, {"best": 994.0, "objective": 994, "avg": 2194.6133333333332, "evals": 11020}, {"best": 994.0, "objective": 994, "avg": 1695.3866666666668, "evals": 11109}, {"best": 994.0, "objective": 994, "avg": 1679.82, "evals": 11180}, {"best": 994.0, "objective": 994, "avg": 2093.2733333333335, "evals": 11291}, {"best": 994.0, "objective": 994, "avg": 1838.08, "evals": 11367}, {"best": 994.0, "objective": 994, "avg": 1507.3133333333333, "evals": 11471}, {"best": 994.0, "objective": 994, "avg": 1509.9266666666667, "evals": 11555}, {"best": 994.0, "objective": 994, "avg": 1969.46, "evals": 11648}, {"best": 994.0, "objective": 994, "avg": 1763.56, "evals": 11733}, {"best": 994.0, "objective": 994, "avg": 2068.28, "evals": 11827}, {"best": 994.0, "objective": 994, "avg": 2054.4333333333334, "evals": 11904}, {"best": 994.0, "objective": 994, "avg": 1867.32, "evals": 11989}, {"best": 994.0, "objective": 994, "avg": 2064.9933333333333, "evals": 12103}, {"best": 994.0, "objective": 994, "avg": 2007.5466666666666, "evals": 12192}, {"best": 994.0, "objective": 994, "avg": 2253.2933333333335, "evals": 12285}, {"best": 994.0, "objective": 994, "avg": 1835.6133333333332, "evals": 12375}, {"best": 994.0, "objective": 994, "avg": 2080.693333333333, "evals": 12467}, {"best": 994.0, "objective": 994, "avg": 1851.7066666666667, "evals": 12562}, {"best": 994.0, "objective": 994, "avg": 1851.3933333333334, "evals": 12661}, {"best": 994.0, "objective": 994, "avg": 1894.44, "evals": 12752}, {"best": 994.0, "objective": 994, "avg": 1706.0866666666666, "evals": 12837}, {"best": 994.0, "objective": 994, "avg": 1667.12, "evals": 12930}, {"best": 994.0, "objective": 994, "avg": 1819.38, "evals": 13024}, {"best": 994.0, "objective": 994, "avg": 1665.74, "evals": 13118}, {"best": 994.0, "objective": 994, "avg": 1779.9533333333334, "evals": 13200}, {"best": 994.0, "objective": 994, "avg": 2365.04, "evals": 13282}, {"best": 994.0, "objective": 994, "avg": 1723.1466666666668, "evals": 13369}, {"best": 994.0, "objective": 994, "avg": 1680.8733333333332, "evals": 13452}, {"best": 994.0, "objective": 994, "avg": 1994.3266666666666, "evals": 13541}, {"best": 994.0, "objective": 994, "avg": 1637.1266666666668, "evals": 13636}, {"best": 994.0, "objective": 994, "avg": 1608.4866666666667, "evals": 13723}, {"best": 994.0, "objective": 994, "avg": 2180.8733333333334, "evals": 13816}, {"best": 994.0, "objective": 994, "avg": 2149.14, "evals": 13910}, {"best": 994.0, "objective": 994, "avg": 1792.6933333333334, "evals": 13997}, {"best": 994.0, "objective": 994, "avg": 2083.2933333333335, "evals": 14077}, {"best": 994.0, "objective": 994, "avg": 1796.6933333333334, "evals": 14169}, {"best": 994.0, "objective": 994, "avg": 1767.0266666666666, "evals": 14248}, {"best": 994.0, "objective": 994, "avg": 2308.2066666666665, "evals": 14330}, {"best": 994.0, "objective": 994, "avg": 1653.5333333333333, "evals": 14417}, {"best": 994.0, "objective": 994, "avg": 1865.52, "evals": 14518}, {"best": 994.0, "objective": 994, "avg": 2568.3333333333335, "evals": 14596}, {"best": 994.0, "objective": 994, "avg": 1726.0333333333333, "evals": 14685}, {"best": 994.0, "objective": 994, "avg": 1823.7733333333333, "evals": 14785}, {"best": 994.0, "objective": 994, "avg": 2124.3, "evals": 14861}, {"best": 994.0, "objective": 994, "avg": 1611.8266666666666, "evals": 14947}, {"best": 994.0, "objective": 994, "avg": 1412.6533333333334, "evals": 15028}, {"best": 994.0, "objective": 994, "avg": 1839.6733333333334, "evals": 15109}, {"best": 994.0, "objective": 994, "avg": 1423.8933333333334, "evals": 15204}, {"best": 994.0, "objective": 994, "avg": 1622.42, "evals": 15294}, {"best": 994.0, "objective": 994, "avg": 2465.4, "evals": 15388}, {"best": 994.0, "objective": 994, "avg": 2125.54, "evals": 15467}, {"best": 994.0, "objective": 994, "avg": 2083.7, "evals": 15555}, {"best": 994.0, "objective": 994, "avg": 2381.4733333333334, "evals": 15650}, {"best": 994.0, "objective": 994, "avg": 1750.88, "evals": 15740}, {"best": 994.0, "objective": 994, "avg": 2324.42, "evals": 15824}, {"best": 994.0, "objective": 994, "avg": 1479.68, "evals": 15916}, {"best": 994.0, "objective": 994, "avg": 1580.08, "evals": 16009}, {"best": 994.0, "objective": 994, "avg": 2336.846666666667, "evals": 16102}, {"best": 994.0, "objective": 994, "avg": 1838.12, "evals": 16189}, {"best": 994.0, "objective": 994, "avg": 2169.9333333333334, "evals": 16282}, {"best": 994.0, "objective": 994, "avg": 2124.04, "evals": 16365}, {"best": 994.0, "objective": 994, "avg": 2024.0266666666666, "evals": 16461}, {"best": 994.0, "objective": 994, "avg": 1823.1266666666668, "evals": 16549}, {"best": 994.0, "objective": 994, "avg": 1639.2533333333333, "evals": 16634}, {"best": 994.0, "objective": 994, "avg": 1723.9866666666667, "evals": 16724}, {"best": 994.0, "objective": 994, "avg": 1806.76, "evals": 16808}, {"best": 994.0, "objective": 994, "avg": 1609.3466666666666, "evals": 16894}, {"best": 994.0, "objective": 994, "avg": 1793.1, "evals": 16978}, {"best": 994.0, "objective": 994, "avg": 2166.6, "evals": 17073}, {"best": 994.0, "objective": 994, "avg": 2371.3133333333335, "evals": 17159}, {"best": 994.0, "objective": 994, "avg": 1797.86, "evals": 17243}, {"best": 994.0, "objective": 994, "avg": 1965.68, "evals": 17337}, {"best": 994.0, "objective": 994, "avg": 1895.0533333333333, "evals": 17427}, {"best": 994.0, "objective": 994, "avg": 1582.66, "evals": 17521}, {"best": 994.0, "objective": 994, "avg": 2322.2733333333335, "evals": 17610}, {"best": 994.0, "objective": 994, "avg": 1737.06, "evals": 17690}, {"best": 994.0, "objective": 994, "avg": 1967.0666666666666, "evals": 17784}, {"best": 994.0, "objective": 994, "avg": 1693.2133333333334, "evals": 17868}, {"best": 994.0, "objective": 994, "avg": 2407.1066666666666, "evals": 17969}, {"best": 994.0, "objective": 994, "avg": 2181.1, "evals": 18067}, {"best": 994.0, "objective": 994, "avg": 1622.9133333333334, "evals": 18153}, {"best": 994.0, "objective": 994, "avg": 1966.42, "evals": 18230}, {"best": 994.0, "objective": 994, "avg": 1981.6133333333332, "evals": 18334}, {"best": 994.0, "objective": 994, "avg": 2078.806666666667, "evals": 18428}, {"best": 994.0, "objective": 994, "avg": 1978.8866666666668, "evals": 18516}, {"best": 994.0, "objective": 994, "avg": 2110.14, "evals": 18612}, {"best": 994.0, "objective": 994, "avg": 2067.6466666666665, "evals": 18718}, {"best": 994.0, "objective": 994, "avg": 2207.52, "evals": 18803}, {"best": 994.0, "objective": 994, "avg": 1749.62, "evals": 18893}, {"best": 994.0, "objective": 994, "avg": 1509.5266666666666, "evals": 18987}, {"best": 994.0, "objective": 994, "avg": 1580.1266666666668, "evals": 19058}, {"best": 994.0, "objective": 994, "avg": 2035.6866666666667, "evals": 19141}, {"best": 994.0, "objective": 994, "avg": 2051.42, "evals": 19228}, {"best": 994.0, "objective": 994, "avg": 1751.9466666666667, "evals": 19314}, {"best": 994.0, "objective": 994, "avg": 2211.4533333333334, "evals": 19412}, {"best": 994.0, "objective": 994, "avg": 1695.3666666666666, "evals": 19495}, {"best": 994.0, "objective": 994, "avg": 2153.153333333333, "evals": 19599}, {"best": 994.0, "objective": 994, "avg": 2166.4, "evals": 19691}, {"best": 994.0, "objective": 994, "avg": 2037.16, "evals": 19789}, {"best": 994.0, "objective": 994, "avg": 2256.3866666666668, "evals": 19873}, {"best": 994.0, "objective": 994, "avg": 1637.7266666666667, "evals": 19954}, {"best": 994.0, "objective": 994, "avg": 1553.16, "evals": 20000}], "best_objective": 994}}