{"fileName": "vc_25_150_07.txt", "graph": {"n": 25, "m": 150, "d": 0.5}, "problemClass": "SPI", "testInstanceName": "150", "testInstanceVersion": "07.txt", "performanceMetrics": {"generations": [{"best": 501.0, "objective": 501, "avg": 805.775, "evals": 325}, {"best": 275.0, "objective": 275, "avg": 696.025, "evals": 442}, {"best": 275.0, "objective": 275, "avg": 590.985, "evals": 568}, {"best": 275.0, "objective": 275, "avg": 506.035, "evals": 694}, {"best": 218.0, "objective": 218, "avg": 441.39, "evals": 800}, {"best": 203.0, "objective": 203, "avg": 392.83, "evals": 930}, {"best": 111.0, "objective": 111, "avg": 346.705, "evals": 1063}, {"best": 111.0, "objective": 111, "avg": 302.655, "evals": 1175}, {"best": 111.0, "objective": 111, "avg": 271.955, "evals": 1311}, {"best": 111.0, "objective": 111, "avg": 233.615, "evals": 1438}, {"best": 111.0, "objective": 111, "avg": 204.075, "evals": 1562}, {"best": 111.0, "objective": 111, "avg": 166.115, "evals": 1657}, {"best": 111.0, "objective": 111, "avg": 149.195, "evals": 1781}, {"best": 111.0, "objective": 111, "avg": 128.91, "evals": 1900}, {"best": 111.0, "objective": 111, "avg": 137.06, "evals": 2029}, {"best": 111.0, "objective": 111, "avg": 138.525, "evals": 2146}, {"best": 111.0, "objective": 111, "avg": 138.825, "evals": 2271}, {"best": 111.0, "objective": 111, "avg": 139.145, "evals": 2387}, {"best": 111.0, "objective": 111, "avg": 142.86, "evals": 2502}, {"best": 111.0, "objective": 111, "avg": 136.395, "evals": 2616}, {"best": 111.0, "objective": 111, "avg": 131.89, "evals": 2734}, {"best": 111.0, "objective": 111, "avg": 138.01, "evals": 2859}, {"best": 111.0, "objective": 111, "avg": 135.2, "evals": 2982}, {"best": 111.0, "objective": 111, "avg": 141.82, "evals": 3111}, {"best": 111.0, "objective": 111, "avg": 132.27, "evals": 3240}, {"best": 111.0, "objective": 111, "avg": 136.49, "evals": 3362}, {"best": 111.0, "objective": 111, "avg": 133.51, "evals": 3491}, {"best": 111.0, "objective": 111, "avg": 136.9, "evals": 3616}, {"best": 111.0, "objective": 111, "avg": 136.225, "evals": 3727}, {"best": 111.0, "objective": 111, "avg": 134.565, "evals": 3829}, {"best": 111.0, "objective": 111, "avg": 144.335, "evals": 3957}, {"best": 111.0, "objective": 111, "avg": 138.475, "evals": 4095}, {"best": 111.0, "objective": 111, "avg": 126.845, "evals": 4215}, {"best": 111.0, "objective": 111, "avg": 132.945, "evals": 4323}, {"best": 111.0, "objective": 111, "avg": 122.78, "evals": 4424}, {"best": 111.0, "objective": 111, "avg": 138.0, "evals": 4533}, {"best": 111.0, "objective": 111, "avg": 134.925, "evals": 4638}, {"best": 111.0, "objective": 111, "avg": 128.145, "evals": 4759}, {"best": 111.0, "objective": 111, "avg": 132.675, "evals": 4888}, {"best": 111.0, "objective": 111, "avg": 129.77, "evals": 5011}, {"best": 111.0, "objective": 111, "avg": 139.515, "evals": 5140}, {"best": 111.0, "objective": 111, "avg": 126.575, "evals": 5276}, {"best": 111.0, "objective": 111, "avg": 139.01, "evals": 5403}, {"best": 111.0, "objective": 111, "avg": 138.585, "evals": 5530}, {"best": 111.0, "objective": 111, "avg": 142.155, "evals": 5658}, {"best": 111.0, "objective": 111, "avg": 133.005, "evals": 5777}, {"best": 111.0, "objective": 111, "avg": 133.495, "evals": 5884}, {"best": 111.0, "objective": 111, "avg": 138.54, "evals": 6000}, {"best": 111.0, "objective": 111, "avg": 132.635, "evals": 6119}, {"best": 111.0, "objective": 111, "avg": 129.86, "evals": 6223}, {"best": 111.0, "objective": 111, "avg": 135.91, "evals": 6335}, {"best": 111.0, "objective": 111, "avg": 135.2, "evals": 6442}, {"best": 111.0, "objective": 111, "avg": 133.975, "evals": 6568}, {"best": 111.0, "objective": 111, "avg": 131.485, "evals": 6691}, {"best": 111.0, "objective": 111, "avg": 132.3, "evals": 6803}, {"best": 111.0, "objective": 111, "avg": 135.355, "evals": 6919}, {"best": 111.0, "objective": 111, "avg": 136.63, "evals": 7033}, {"best": 111.0, "objective": 111, "avg": 138.685, "evals": 7151}, {"best": 111.0, "objective": 111, "avg": 135.345, "evals": 7278}, {"best": 111.0, "objective": 111, "avg": 132.905, "evals": 7383}, {"best": 111.0, "objective": 111, "avg": 134.59, "evals": 7509}, {"best": 111.0, "objective": 111, "avg": 134.38, "evals": 7636}, {"best": 111.0, "objective": 111, "avg": 130.225, "evals": 7747}, {"best": 111.0, "objective": 111, "avg": 128.965, "evals": 7857}, {"best": 111.0, "objective": 111, "avg": 125.74, "evals": 7976}, {"best": 111.0, "objective": 111, "avg": 134.605, "evals": 8098}, {"best": 111.0, "objective": 111, "avg": 142.6, "evals": 8208}, {"best": 111.0, "objective": 111, "avg": 126.82, "evals": 8325}, {"best": 111.0, "objective": 111, "avg": 132.72, "evals": 8426}, {"best": 111.0, "objective": 111, "avg": 127.635, "evals": 8558}, {"best": 111.0, "objective": 111, "avg": 136.19, "evals": 8702}, {"best": 111.0, "objective": 111, "avg": 142.03, "evals": 8830}, {"best": 111.0, "objective": 111, "avg": 129.445, "evals": 8953}, {"best": 111.0, "objective": 111, "avg": 137.445, "evals": 9057}, {"best": 111.0, "objective": 111, "avg": 135.295, "evals": 9171}, {"best": 111.0, "objective": 111, "avg": 142.845, "evals": 9295}, {"best": 111.0, "objective": 111, "avg": 136.03, "evals": 9416}, {"best": 111.0, "objective": 111, "avg": 128.74, "evals": 9541}, {"best": 111.0, "objective": 111, "avg": 134.03, "evals": 9672}, {"best": 111.0, "objective": 111, "avg": 129.06, "evals": 9784}, {"best": 111.0, "objective": 111, "avg": 135.32, "evals": 9904}, {"best": 111.0, "objective": 111, "avg": 130.865, "evals": 10033}, {"best": 111.0, "objective": 111, "avg": 136.68, "evals": 10147}, {"best": 111.0, "objective": 111, "avg": 135.515, "evals": 10268}, {"best": 111.0, "objective": 111, "avg": 129.295, "evals": 10386}, {"best": 111.0, "objective": 111, "avg": 130.035, "evals": 10517}, {"best": 111.0, "objective": 111, "avg": 133.835, "evals": 10629}, {"best": 111.0, "objective": 111, "avg": 128.205, "evals": 10747}, {"best": 111.0, "objective": 111, "avg": 138.235, "evals": 10864}, {"best": 111.0, "objective": 111, "avg": 131.49, "evals": 10983}, {"best": 111.0, "objective": 111, "avg": 137.835, "evals": 11109}, {"best": 111.0, "objective": 111, "avg": 134.655, "evals": 11235}, {"best": 111.0, "objective": 111, "avg": 135.52, "evals": 11367}, {"best": 111.0, "objective": 111, "avg": 128.79, "evals": 11487}, {"best": 111.0, "objective": 111, "avg": 144.725, "evals": 11604}, {"best": 111.0, "objective": 111, "avg": 141.425, "evals": 11727}, {"best": 111.0, "objective": 111, "avg": 139.54, "evals": 11857}, {"best": 111.0, "objective": 111, "avg": 142.025, "evals": 11981}, {"best": 111.0, "objective": 111, "avg": 133.465, "evals": 12102}, {"best": 111.0, "objective": 111, "avg": 134.03, "evals": 12225}, {"best": 111.0, "objective": 111, "avg": 135.7, "evals": 12337}, {"best": 111.0, "objective": 111, "avg": 133.915, "evals": 12447}, {"best": 111.0, "objective": 111, "avg": 133.815, "evals": 12585}, {"best": 111.0, "objective": 111, "avg": 129.465, "evals": 12704}, {"best": 111.0, "objective": 111, "avg": 130.215, "evals": 12830}, {"best": 111.0, "objective": 111, "avg": 130.72, "evals": 12955}, {"best": 111.0, "objective": 111, "avg": 135.025, "evals": 13071}, {"best": 111.0, "objective": 111, "avg": 140.045, "evals": 13196}, {"best": 111.0, "objective": 111, "avg": 138.085, "evals": 13324}, {"best": 111.0, "objective": 111, "avg": 141.48, "evals": 13448}, {"best": 111.0, "objective": 111, "avg": 135.95, "evals": 13568}, {"best": 111.0, "objective": 111, "avg": 138.895, "evals": 13690}, {"best": 111.0, "objective": 111, "avg": 131.05, "evals": 13794}, {"best": 111.0, "objective": 111, "avg": 131.875, "evals": 13913}, {"best": 111.0, "objective": 111, "avg": 133.765, "evals": 14035}, {"best": 111.0, "objective": 111, "avg": 134.165, "evals": 14160}, {"best": 111.0, "objective": 111, "avg": 143.33, "evals": 14286}, {"best": 111.0, "objective": 111, "avg": 141.7, "evals": 14405}, {"best": 111.0, "objective": 111, "avg": 126.84, "evals": 14522}, {"best": 111.0, "objective": 111, "avg": 134.28, "evals": 14644}, {"best": 111.0, "objective": 111, "avg": 142.37, "evals": 14768}, {"best": 111.0, "objective": 111, "avg": 142.295, "evals": 14890}, {"best": 111.0, "objective": 111, "avg": 134.215, "evals": 15025}, {"best": 111.0, "objective": 111, "avg": 127.32, "evals": 15132}, {"best": 111.0, "objective": 111, "avg": 129.76, "evals": 15256}, {"best": 111.0, "objective": 111, "avg": 132.695, "evals": 15380}, {"best": 111.0, "objective": 111, "avg": 141.47, "evals": 15490}, {"best": 111.0, "objective": 111, "avg": 144.595, "evals": 15603}, {"best": 111.0, "objective": 111, "avg": 131.43, "evals": 15720}, {"best": 111.0, "objective": 111, "avg": 138.915, "evals": 15839}, {"best": 111.0, "objective": 111, "avg": 139.89, "evals": 15972}, {"best": 111.0, "objective": 111, "avg": 127.115, "evals": 16090}, {"best": 111.0, "objective": 111, "avg": 133.94, "evals": 16213}, {"best": 111.0, "objective": 111, "avg": 133.215, "evals": 16339}, {"best": 111.0, "objective": 111, "avg": 130.08, "evals": 16441}, {"best": 111.0, "objective": 111, "avg": 145.005, "evals": 16558}, {"best": 111.0, "objective": 111, "avg": 131.69, "evals": 16679}, {"best": 111.0, "objective": 111, "avg": 128.095, "evals": 16802}, {"best": 111.0, "objective": 111, "avg": 134.845, "evals": 16915}, {"best": 111.0, "objective": 111, "avg": 134.825, "evals": 17035}, {"best": 111.0, "objective": 111, "avg": 135.815, "evals": 17161}, {"best": 111.0, "objective": 111, "avg": 130.855, "evals": 17268}, {"best": 111.0, "objective": 111, "avg": 138.055, "evals": 17386}, {"best": 111.0, "objective": 111, "avg": 139.75, "evals": 17509}, {"best": 111.0, "objective": 111, "avg": 124.81, "evals": 17623}, {"best": 111.0, "objective": 111, "avg": 134.05, "evals": 17741}, {"best": 111.0, "objective": 111, "avg": 131.06, "evals": 17862}, {"best": 111.0, "objective": 111, "avg": 144.98, "evals": 17987}, {"best": 111.0, "objective": 111, "avg": 135.945, "evals": 18118}, {"best": 111.0, "objective": 111, "avg": 135.135, "evals": 18249}, {"best": 111.0, "objective": 111, "avg": 139.87, "evals": 18369}, {"best": 111.0, "objective": 111, "avg": 141.55, "evals": 18482}, {"best": 111.0, "objective": 111, "avg": 137.23, "evals": 18602}, {"best": 111.0, "objective": 111, "avg": 135.92, "evals": 18732}, {"best": 111.0, "objective": 111, "avg": 136.24, "evals": 18837}, {"best": 111.0, "objective": 111, "avg": 129.245, "evals": 18950}, {"best": 111.0, "objective": 111, "avg": 130.275, "evals": 19068}, {"best": 111.0, "objective": 111, "avg": 124.84, "evals": 19191}, {"best": 111.0, "objective": 111, "avg": 139.56, "evals": 19295}, {"best": 111.0, "objective": 111, "avg": 139.265, "evals": 19419}, {"best": 111.0, "objective": 111, "avg": 127.885, "evals": 19524}, {"best": 111.0, "objective": 111, "avg": 131.35, "evals": 19653}, {"best": 111.0, "objective": 111, "avg": 130.755, "evals": 19768}, {"best": 111.0, "objective": 111, "avg": 124.315, "evals": 19858}, {"best": 111.0, "objective": 111, "avg": 136.305, "evals": 19965}, {"best": 111.0, "objective": 111, "avg": 1103.35, "evals": 20000}], "best": 111.0, "is_best_correct": true, "objective": 111}}